capcruncher/__init__.py
capcruncher/_version.py
capcruncher/utils.py
capcruncher/api/__init__.py
capcruncher/api/annotate.py
capcruncher/api/deduplicate.py
capcruncher/api/filter.py
capcruncher/api/io.py
capcruncher/api/pileup.py
capcruncher/api/plotting.py
capcruncher/api/statistics.py
capcruncher/api/storage.py
capcruncher/cli/__init__.py
capcruncher/cli/alignments_annotate.py
capcruncher/cli/alignments_filter.py
capcruncher/cli/cli_alignments.py
capcruncher/cli/cli_fastq.py
capcruncher/cli/cli_genome.py
capcruncher/cli/cli_interactions.py
capcruncher/cli/cli_pipeline.py
capcruncher/cli/cli_plot.py
capcruncher/cli/cli_utilities.py
capcruncher/cli/fastq_deduplicate.py
capcruncher/cli/fastq_digest.py
capcruncher/cli/fastq_split.py
capcruncher/cli/genome_digest.py
capcruncher/cli/interactions_compare.py
capcruncher/cli/interactions_count.py
capcruncher/cli/interactions_deduplicate.py
capcruncher/cli/interactions_differential.py
capcruncher/cli/interactions_pileup.py
capcruncher/cli/interactions_store.py
capcruncher/data/logo.txt
capcruncher/pipeline/utils.py
capcruncher/pipeline/config/cookiecutter.json
capcruncher/pipeline/config/{{cookiecutter.date}}_{{cookiecutter.__project_id}}_{{cookiecutter.__assay}}/capcruncher_config.yml
capcruncher/pipeline/workflow/Snakefile
capcruncher/pipeline/workflow/data/annotation_defaults.json
capcruncher/pipeline/workflow/envs/environment.yml
capcruncher/pipeline/workflow/envs/profiles/profile_drmaa_singularity/config.yaml
capcruncher/pipeline/workflow/envs/profiles/profile_singularity/config.yaml
capcruncher/pipeline/workflow/report/capcruncher_report.qmd
capcruncher/pipeline/workflow/report/make_report.py
capcruncher/pipeline/workflow/report/report_text.yml
capcruncher/pipeline/workflow/rules/align.smk
capcruncher/pipeline/workflow/rules/annotate.smk
capcruncher/pipeline/workflow/rules/compare.smk
capcruncher/pipeline/workflow/rules/digest.smk
capcruncher/pipeline/workflow/rules/fastq.smk
capcruncher-0.3.12.dist-info/LICENSE
capcruncher-0.3.12.dist-info/METADATA
capcruncher-0.3.12.dist-info/WHEEL
capcruncher-0.3.12.dist-info/entry_points.txt
capcruncher-0.3.12.dist-info/top_level.txt
capcruncher-0.3.12.dist-info/RECORD
