Metadata-Version: 2.1
Name: capcruncher
Version: 0.3.12
Summary: An end-to-end solution for processing Capture-C, Tri-C and Tiled-C data
Author-email: Alastair Smith <alastair.smith@ndcls.ox.ac.uk>
License: GNU GENERAL PUBLIC LICENSE
Project-URL: repo, https://github.com/sims-lab/CapCruncher.git
Requires-Python: >=3.10
License-File: LICENSE
Requires-Dist: click <=8.2.0
Requires-Dist: cookiecutter <=2.1.1
Requires-Dist: loguru <=0.7.2
Requires-Dist: more-itertools
Requires-Dist: numpy <=1.26.4
Requires-Dist: pandas <=2.1.2
Requires-Dist: polars
Requires-Dist: PuLP <2.8.0
Requires-Dist: pyarrow
Requires-Dist: pybedtools
Requires-Dist: pyranges <=0.0.129
Requires-Dist: snakemake-wrapper-utils
Requires-Dist: snakemake <=7.32.4
Provides-Extra: full
Requires-Dist: click <=8.2.0 ; extra == 'full'
Requires-Dist: cookiecutter <=2.1.1 ; extra == 'full'
Requires-Dist: loguru <=0.7.2 ; extra == 'full'
Requires-Dist: more-itertools ; extra == 'full'
Requires-Dist: numpy <=1.26.4 ; extra == 'full'
Requires-Dist: pandas <=2.1.2 ; extra == 'full'
Requires-Dist: PuLP <2.8.0 ; extra == 'full'
Requires-Dist: pyranges <=0.0.129 ; extra == 'full'
Requires-Dist: snakemake-wrapper-utils ; extra == 'full'
Requires-Dist: snakemake <=7.32.4 ; extra == 'full'
Requires-Dist: capcruncher-tools >=0.2.0 ; extra == 'full'
Requires-Dist: coolbox ; extra == 'full'
Requires-Dist: cooler <=0.9.2 ; extra == 'full'
Requires-Dist: h5py ; extra == 'full'
Requires-Dist: ibis-framework[duckdb] <=8.0.0,>6.1.0 ; extra == 'full'
Requires-Dist: multiqc ; extra == 'full'
Requires-Dist: matplotlib >=3.4.1 ; extra == 'full'
Requires-Dist: pandera <=0.17.2 ; extra == 'full'
Requires-Dist: panel <=1.3.0 ; extra == 'full'
Requires-Dist: papermill ; extra == 'full'
Requires-Dist: plotly <=5.18.0,>5.0.0 ; extra == 'full'
Requires-Dist: polars <=0.19.15 ; extra == 'full'
Requires-Dist: pyarrow <15.0.0,>11.0.0 ; extra == 'full'
Requires-Dist: pybedtools <=0.9.0 ; extra == 'full'
Requires-Dist: pydantic <2.6.0,>2.4.0 ; extra == 'full'
Requires-Dist: pydeseq2 ; extra == 'full'
Requires-Dist: pysam <=0.21.0,>0.15.0 ; extra == 'full'
Requires-Dist: quarto ; extra == 'full'
Requires-Dist: ray >=2.8.0 ; extra == 'full'
Requires-Dist: seaborn <=0.12.2 ; extra == 'full'
Requires-Dist: toml ; extra == 'full'
Requires-Dist: tqdm <=4.65.0 ; extra == 'full'
Requires-Dist: trackhub <=0.2.4 ; extra == 'full'
Requires-Dist: tracknado ; extra == 'full'
Requires-Dist: ujson <=5.7.0 ; extra == 'full'
Requires-Dist: xopen ; extra == 'full'
Requires-Dist: xxhash <=3.4.1 ; extra == 'full'
